LICENSE.md
MANIFEST.in
README.rst
pyproject.toml
requirements.core.txt
setup.py
core_explore_example_app/__init__.py
core_explore_example_app/admin.py
core_explore_example_app/apps.py
core_explore_example_app/discover.py
core_explore_example_app/menus.py
core_explore_example_app/models.py
core_explore_example_app/settings.py
core_explore_example_app/tasks.py
core_explore_example_app/urls.py
core_explore_example_app.egg-info/PKG-INFO
core_explore_example_app.egg-info/SOURCES.txt
core_explore_example_app.egg-info/dependency_links.txt
core_explore_example_app.egg-info/requires.txt
core_explore_example_app.egg-info/top_level.txt
core_explore_example_app/commons/__init__.py
core_explore_example_app/commons/exceptions.py
core_explore_example_app/components/__init__.py
core_explore_example_app/components/explore_data_structure/__init__.py
core_explore_example_app/components/explore_data_structure/admin_site.py
core_explore_example_app/components/explore_data_structure/api.py
core_explore_example_app/components/explore_data_structure/models.py
core_explore_example_app/components/persistent_query_example/__init__.py
core_explore_example_app/components/persistent_query_example/admin_site.py
core_explore_example_app/components/persistent_query_example/api.py
core_explore_example_app/components/persistent_query_example/models.py
core_explore_example_app/components/saved_query/__init__.py
core_explore_example_app/components/saved_query/admin_site.py
core_explore_example_app/components/saved_query/api.py
core_explore_example_app/components/saved_query/models.py
core_explore_example_app/migrations/0001_initial.py
core_explore_example_app/migrations/__init__.py
core_explore_example_app/permissions/__init__.py
core_explore_example_app/permissions/discover.py
core_explore_example_app/permissions/rights.py
core_explore_example_app/rest/__init__.py
core_explore_example_app/rest/urls.py
core_explore_example_app/rest/persistent_query_example/__init__.py
core_explore_example_app/rest/persistent_query_example/serializers.py
core_explore_example_app/rest/persistent_query_example/views.py
core_explore_example_app/rest/saved_query/__init__.py
core_explore_example_app/rest/saved_query/serializers.py
