Metadata-Version: 2.1
Name: core-explore-example-app
Version: 2.19.0
Summary: Exploration by example for the curator core project
Home-page: https://github.com/usnistgov/core_explore_example_app
Author: NIST IT Lab
Author-email: itl_inquiries@nist.gov
License-File: LICENSE.md
